{
    "MEGCoordinateSystem": "ElektaNeuromag",
    "MEGCoordinateUnits": "m",
    "MEGCoordinateSystemDescription": "RAS orientation and the origin between the ears",
    "HeadCoilCoordinates": {
        "NAS": [
            -9.313225746154785e-10,
            0.09157215058803558,
            -7.450580596923828e-09
        ],
        "LPA": [
            -0.06497380137443542,
            0.0,
            0.0
        ],
        "RPA": [
            0.06233365461230278,
            1.4901161193847656e-08,
            3.725290298461914e-09
        ],
        "coil1": [
            0.03227144479751587,
            0.0889391303062439,
            0.048807449638843536
        ],
        "coil2": [
            -0.03280821070075035,
            0.08731144666671753,
            0.06002684682607651
        ],
        "coil3": [
            0.06794733554124832,
            -0.016168907284736633,
            0.013119567185640335
        ],
        "coil4": [
            -0.06277540326118469,
            -0.024063289165496826,
            0.004052642732858658
        ]
    },
    "HeadCoilCoordinateSystem": "ElektaNeuromag",
    "HeadCoilCoordinateUnits": "m",
    "AnatomicalLandmarkCoordinates": {
        "NAS": [
            -9.313225746154785e-10,
            0.09157215058803558,
            -7.450580596923828e-09
        ],
        "LPA": [
            -0.06497380137443542,
            0.0,
            0.0
        ],
        "RPA": [
            0.06233365461230278,
            1.4901161193847656e-08,
            3.725290298461914e-09
        ],
        "coil1": [
            0.03227144479751587,
            0.0889391303062439,
            0.048807449638843536
        ],
        "coil2": [
            -0.03280821070075035,
            0.08731144666671753,
            0.06002684682607651
        ],
        "coil3": [
            0.06794733554124832,
            -0.016168907284736633,
            0.013119567185640335
        ],
        "coil4": [
            -0.06277540326118469,
            -0.024063289165496826,
            0.004052642732858658
        ]
    },
    "AnatomicalLandmarkCoordinateSystem": "ElektaNeuromag",
    "AnatomicalLandmarkCoordinateUnits": "m"
}
